qctrlcirq/__init__.py
qctrlcirq/circuit.py
qctrlcirq/schedule.py
qctrl_cirq-0.0.5.dist-info/LICENSE
qctrl_cirq-0.0.5.dist-info/WHEEL
qctrl_cirq-0.0.5.dist-info/METADATA
qctrl_cirq-0.0.5.dist-info/RECORD
