Metadata-Version: 2.1
Name: qctrl-cirq
Version: 0.0.5
Summary: Q-CTRL Python Cirq
Home-page: https://q-ctrl.com
License: Apache-2.0
Keywords: q-ctrl,qctrl,quantum control
Author: Q-CTRL
Author-email: support@q-ctrl.com
Maintainer: Q-CTRL
Maintainer-email: support@q-ctrl.com
Requires-Python: >=3.7,<3.9
Classifier: Development Status :: 5 - Production/Stable
Classifier: Environment :: Console
Classifier: Intended Audience :: Developers
Classifier: Intended Audience :: Education
Classifier: Intended Audience :: Science/Research
Classifier: License :: OSI Approved :: Apache Software License
Classifier: Natural Language :: English
Classifier: Operating System :: OS Independent
Classifier: Programming Language :: Python :: 3
Classifier: Programming Language :: Python :: 3.6
Classifier: Programming Language :: Python :: 3.7
Classifier: Programming Language :: Python :: 3.8
Classifier: Topic :: Internet :: WWW/HTTP
Classifier: Topic :: Scientific/Engineering :: Physics
Classifier: Topic :: Scientific/Engineering :: Visualization
Classifier: Topic :: Software Development :: Embedded Systems
Classifier: Topic :: System :: Distributed Computing
Requires-Dist: cirq (>=0.6.0,<0.7.0)
Requires-Dist: numpy (>=1.16,<2.0)
Requires-Dist: qctrl-open-controls (>=8.5.1,<9.0.0)
Requires-Dist: scipy (>=1.3,<2.0)
Requires-Dist: toml (>=0.10.0,<0.11.0)
Project-URL: GitHub, https://github.com/qctrl
Project-URL: Repository, https://github.com/qctrl/python-cirq
Project-URL: Twitter, https://twitter.com/qctrlHQ
